setup.py
greennet/__init__.py
greennet/hub.py
greennet/queue.py
greennet/ssl.py
greennet/trigger.py
greennet/util.py
greennet.egg-info/PKG-INFO
greennet.egg-info/SOURCES.txt
greennet.egg-info/dependency_links.txt
greennet.egg-info/requires.txt
greennet.egg-info/top_level.txt
tests/__init__.py
tests/test_hub.py
tests/test_queue.py
tests/testall.py