Metadata-Version: 1.0
Name: greennet
Version: 0.1.0
Summary: A greenlet-based task scheduler
Home-page: http://zognot.org/projects/greennet/
Author: David Hain
Author-email: dhain@zognot.org
License: MIT
Platform: UNKNOWN
Classifier: Development Status :: 4 - Beta
Classifier: Intended Audience :: Developers
Classifier: License :: OSI Approved :: MIT License
Classifier: Operating System :: MacOS :: MacOS X
Classifier: Operating System :: POSIX
Classifier: Programming Language :: Python
Classifier: Topic :: Software Development :: Libraries :: Python Modules
